sdo_hmi_rvs/__init__.py
sdo_hmi_rvs/examples/__init__.py
sdo_hmi_rvs/source/__init__.py
sdo_hmi_rvs/source/rv_pipeline.py
sdo_hmi_rvs/tools/__init__.py
sdo_hmi_rvs/tools/calculation_funcs.py
sdo_hmi_rvs/tools/coord_funcs.py
sdo_hmi_rvs/tools/lbc_funcs.py
sdo_hmi_rvs/tools/plotting_funcs.py
sdo_hmi_rvs/tools/rvs.py
sdo_hmi_rvs/tools/settings.py
sdo_hmi_rvs/tools/settings_tamar.py
sdo_hmi_rvs/tools/settings_template.py
sdo_hmi_rvs/tools/utilities.py
sdo_hmi_rvs-0.1.3.dist-info/LICENSE
sdo_hmi_rvs-0.1.3.dist-info/METADATA
sdo_hmi_rvs-0.1.3.dist-info/WHEEL
sdo_hmi_rvs-0.1.3.dist-info/top_level.txt
sdo_hmi_rvs-0.1.3.dist-info/RECORD
