Metadata-Version: 2.1
Name: sdo_hmi_rvs
Version: 0.1.3
Summary: Python package to calculate 'sun-as-a-star' RVs.
Home-page: https://github.com/tamarervin/sdo_hmi_rvs
Author: Tamar Ervin
Author-email: tamarervin@gmail.com
License: Apache Software License
Platform: UNKNOWN
License-File: LICENSE
